CHANGES.rst
LICENSE
MANIFEST.in
README.rst
setup.py
mlask/__init__.py
mlask/mlask.py
mlask/emotemes/emofreqs-short.txt
mlask/emotemes/emofreqs_long.txt
mlask/emotemes/emotemes_all.txt
mlask/emotemes/emotikony_uncoded.txt
mlask/emotemes/emotikony_uncoded_zbakslaszowane.txt
mlask/emotemes/emotikony_unique_chars.txt
mlask/emotemes/emotikony_unique_chars_backup.txt
mlask/emotemes/emotikony_unique_chars_unique.txt
mlask/emotemes/endearments_uncoded.txt
mlask/emotemes/exclamation_uncoded.txt
mlask/emotemes/gitaigo_uncoded.txt
mlask/emotemes/interjections_uncoded.txt
mlask/emotemes/interkon_uncoded.txt
mlask/emotemes/interkonprzed_uncoded.txt
mlask/emotemes/vulgar_uncoded.txt
mlask/emotions/aware_uncoded.txt
mlask/emotions/haji_uncoded.txt
mlask/emotions/ikari_uncoded.txt
mlask/emotions/iya_uncoded.txt
mlask/emotions/kowa_uncoded.txt
mlask/emotions/odoroki_uncoded.txt
mlask/emotions/suki_uncoded.txt
mlask/emotions/takaburi_uncoded.txt
mlask/emotions/yasu_uncoded.txt
mlask/emotions/yorokobi_uncoded.txt
pymlask.egg-info/PKG-INFO
pymlask.egg-info/SOURCES.txt
pymlask.egg-info/dependency_links.txt
pymlask.egg-info/top_level.txt