Metadata-Version: 1.1
Name: pymlask
Version: 0.2.5
Summary: Emotion analyzer for Japanese
Home-page: https://github.com/ikegami-yukino/pymlask
Author: Yukino Ikegami
Author-email: yknikgm@gmail.com
License: The BSD 3-Clause License
Keywords: emotion analysis
Platform: POSIX
Platform: Windows
Platform: Unix
Platform: MacOS
Classifier: Development Status :: 3 - Alpha
Classifier: Intended Audience :: Developers
Classifier: Intended Audience :: Information Technology
Classifier: License :: OSI Approved :: BSD License
Classifier: Natural Language :: Japanese
Classifier: Programming Language :: Python :: 2.6
Classifier: Programming Language :: Python :: 2.7
Classifier: Programming Language :: Python :: 3.3
Classifier: Programming Language :: Python :: 3.4
Classifier: Programming Language :: Python :: 3.5
Classifier: Programming Language :: Python :: 3.6
Classifier: Topic :: Text Processing :: Linguistic
